ayx_plugin_cli/__init__.py
ayx_plugin_cli/__main__.py
ayx_plugin_cli/exceptions.py
ayx_plugin_cli/node_js_helpers.py
ayx_plugin_cli/validation.py
ayx_plugin_cli/version.py
ayx_plugin_cli/assets/__init__.py
ayx_plugin_cli/assets/templates/python/README_tests.md
ayx_plugin_cli/assets/templates/python/__init__.j2
ayx_plugin_cli/assets/templates/python/clean_plugin_tests.j2
ayx_plugin_cli/assets/templates/python/plugin.j2
ayx_plugin_cli/assets/templates/python/plugin_tests.j2
ayx_plugin_cli/assets/templates/python/requirements-local.j2
ayx_plugin_cli/assets/templates/python/requirements-thirdparty.j2
ayx_plugin_cli/assets/templates/python/setup.j2
ayx_plugin_cli/assets/templates/python/workspace_bootstrap.j2
ayx_plugin_cli/assets/templates/python/macros/input.j2
ayx_plugin_cli/assets/templates/python/macros/multi_conn.j2
ayx_plugin_cli/assets/templates/python/macros/multi_input.j2
ayx_plugin_cli/assets/templates/python/macros/multi_output.j2
ayx_plugin_cli/assets/templates/python/macros/optional.j2
ayx_plugin_cli/assets/templates/python/macros/output.j2
ayx_plugin_cli/assets/templates/python/macros/passthrough.j2
ayx_plugin_cli/assets/workspace_files/.gitignore
ayx_plugin_cli/assets/workspace_files/README.md
ayx_plugin_cli/assets/workspace_files/default_package_icon.png
ayx_plugin_cli/assets/workspace_files/ui_artifact.zip
ayx_plugin_cli/assets/workspace_files/yxi_bootstrap.py
ayx_plugin_cli/assets/workspace_files/ui_template/README.md
ayx_plugin_cli/ayx_workspace/__init__.py
ayx_plugin_cli/ayx_workspace/constants.py
ayx_plugin_cli/ayx_workspace/template_engine.py
ayx_plugin_cli/ayx_workspace/template_tool_settings.py
ayx_plugin_cli/ayx_workspace/doit/__init__.py
ayx_plugin_cli/ayx_workspace/doit/dodo.py
ayx_plugin_cli/ayx_workspace/doit/build_tasks/__init__.py
ayx_plugin_cli/ayx_workspace/doit/build_tasks/create_plugin.py
ayx_plugin_cli/ayx_workspace/doit/build_tasks/create_yxi.py
ayx_plugin_cli/ayx_workspace/doit/build_tasks/generate_artifact.py
ayx_plugin_cli-1.3.1.dist-info/licenses/LICENSE
ayx_plugin_cli-1.3.1.dist-info/METADATA
ayx_plugin_cli-1.3.1.dist-info/WHEEL
ayx_plugin_cli-1.3.1.dist-info/entry_points.txt
ayx_plugin_cli-1.3.1.dist-info/top_level.txt
ayx_plugin_cli-1.3.1.dist-info/RECORD
