Metadata-Version: 2.4
Name: ayx_plugin_cli
Version: 1.3.1
Summary: The Alteryx command line interface for using Alteryx SDKs.
Author: Alteryx, Inc.
Author-email: support@alteryx.com
Platform: Windows
Classifier: Development Status :: 5 - Production/Stable
Classifier: Intended Audience :: Developers
Classifier: License :: Other/Proprietary License
Classifier: Operating System :: Microsoft :: Windows
Classifier: Programming Language :: Python :: 3.8
Classifier: Topic :: Scientific/Engineering :: Information Analysis
Requires-Python: >=3.8
License-File: LICENSE
Requires-Dist: typer==0.9.0
Requires-Dist: doit==0.36.0
Requires-Dist: packaging==24.2
Requires-Dist: pydantic==2.10.6
Requires-Dist: pytest>=5.4.1
Requires-Dist: requests>=2.32.4
Requires-Dist: xmltodict==0.12.0
Requires-Dist: jinja2==3.1.6
Requires-Dist: MarkupSafe==2.1.4
Requires-Dist: urllib3>=2.5.0
Dynamic: author
Dynamic: author-email
Dynamic: classifier
Dynamic: description
Dynamic: description-content-type
Dynamic: license-file
Dynamic: platform
Dynamic: requires-dist
Dynamic: requires-python
Dynamic: summary
